{
  "selected_model": "Calibrated Random Forest",
  "selection_metric": "log_loss",
  "accuracy": 0.5962406932747467,
  "log_loss": 0.8896577539453819,
  "classes": [
    "AWAY_WIN",
    "DRAW",
    "HOME_WIN"
  ],
  "target_column": "result",
  "feature_columns": [
    "home_team",
    "away_team",
    "tournament",
    "city",
    "country",
    "neutral",
    "year",
    "month",
    "day_of_week",
    "home_team_matches_before",
    "away_team_matches_before",
    "home_avg_goals_for_last_10",
    "away_avg_goals_for_last_10",
    "home_avg_goals_against_last_10",
    "away_avg_goals_against_last_10",
    "home_avg_points_last_10",
    "away_avg_points_last_10",
    "home_win_rate_last_10",
    "away_win_rate_last_10",
    "home_clean_sheet_rate_last_10",
    "away_clean_sheet_rate_last_10",
    "home_failed_to_score_rate_last_10",
    "away_failed_to_score_rate_last_10",
    "experience_diff",
    "goals_for_diff_last_10",
    "goals_against_diff_last_10",
    "points_diff_last_10",
    "win_rate_diff_last_10",
    "clean_sheet_rate_diff_last_10",
    "failed_to_score_rate_diff_last_10",
    "home_elo_before",
    "away_elo_before",
    "elo_diff_before",
    "home_expected_score",
    "away_expected_score"
  ],
  "categorical_features": [
    "home_team",
    "away_team",
    "tournament",
    "city",
    "country"
  ],
  "numeric_features": [
    "neutral",
    "year",
    "month",
    "day_of_week",
    "home_team_matches_before",
    "away_team_matches_before",
    "home_avg_goals_for_last_10",
    "away_avg_goals_for_last_10",
    "home_avg_goals_against_last_10",
    "away_avg_goals_against_last_10",
    "home_avg_points_last_10",
    "away_avg_points_last_10",
    "home_win_rate_last_10",
    "away_win_rate_last_10",
    "home_clean_sheet_rate_last_10",
    "away_clean_sheet_rate_last_10",
    "home_failed_to_score_rate_last_10",
    "away_failed_to_score_rate_last_10",
    "experience_diff",
    "goals_for_diff_last_10",
    "goals_against_diff_last_10",
    "points_diff_last_10",
    "win_rate_diff_last_10",
    "clean_sheet_rate_diff_last_10",
    "failed_to_score_rate_diff_last_10",
    "home_elo_before",
    "away_elo_before",
    "elo_diff_before",
    "home_expected_score",
    "away_expected_score"
  ],
  "train_rows": 41297,
  "test_rows": 8193,
  "time_split": {
    "train": "year < 2018",
    "test": "year >= 2018"
  },
  "calibration": {
    "included": true,
    "method": "sigmoid",
    "cv": 3,
    "note": "Best model is selected by log loss, not accuracy."
  }
}